[
  {
    "Id": "EVT-01",
    "DateHeure": "26/01/1993",
    "Evt": "Arr9t (Jurisprudence)",
    "Cat": "M\u00e9dical",
    "Emetteur": "Cour de cassation (Cass. Com.)",
    "Destinataire": "S\u00e9bastien GRAZIDE",
    "Desc": "Arr9t n\u00b0 91-11.207 relatif \u00e0 la survie de la personnalit\u00e9 morale d'une soci\u00e9t\u00e9 pour les besoins de sa liquidation.",
    "Montant": "Non pr\u00e9cis\u00e9",
    "ITT": "",
    "RefPiece": "11",
    "Portee": "",
    "LienGDrive": "",
    "Statut": "Pr\u00e9c\u00e9dent juridique"
  },
  {
    "Id": "EVT-02",
    "DateHeure": "25/02/2000",
    "Evt": "Arr9t (Jurisprudence)",
    "Cat": "M\u00e9dical",
    "Emetteur": "Cour de cassation (Ass. Pl\u00e9n.)",
    "Destinataire": "S\u00e9bastien GRAZIDE",
    "Desc": "Arr9t Costedoat (n\u00b0 97-17.378) : principe d'immunit\u00e9 civile du pr\u00e9pos\u00e9 agissant dans le cadre de sa mission.",
    "Montant": "Non pr\u00e9cis\u00e9",
    "ITT": "",
    "RefPiece": "11",
    "Portee": "",
    "LienGDrive": "",
    "Statut": "Pr\u00e9c\u00e9dent juridique"
  },
  {
    "Id": "EVT-03",
    "DateHeure": "14/12/2001",
    "Evt": "Arr9t (Jurisprudence)",
    "Cat": "M\u00e9dical",
    "Emetteur": "Cour de cassation (Ass. Pl\u00e9n.)",
    "Destinataire": "S\u00e9bastien GRAZIDE",
    "Desc": "Arr9t Cousin (n\u00b0 00-82.066) : lev\u00e9e de l'immunit\u00e9 du pr\u00e9pos\u00e9 en cas d'infraction p\u00e9nale intentionnelle.",
    "Montant": "Non pr\u00e9cis\u00e9",
    "ITT": "",
    "RefPiece": "11",
    "Portee": "",
    "LienGDrive": "",
    "Statut": "Pr\u00e9c\u00e9dent juridique"
  },
  {
    "Id": "EVT-04",
    "DateHeure": "20/05/2003",
    "Evt": "Arr9t (Jurisprudence)",
    "Cat": "M\u00e9dical",
    "Emetteur": "Cour de cassation (Ch. Com.)",
    "Destinataire": "S\u00e9bastien GRAZIDE",
    "Desc": "Arr9t SATI (n\u00b0 99-17.092) d\u00e9finissant la faute d\u00e9tachable du dirigeant.",
    "Montant": "Non pr\u00e9cis\u00e9",
    "ITT": "",
    "RefPiece": "11",
    "Portee": "",
    "LienGDrive": "",
    "Statut": "Pr\u00e9c\u00e9dent juridique"
  },
  {
    "Id": "EVT-05",
    "DateHeure": "02/01/2008",
    "Evt": "Arr9t (Jurisprudence)",
    "Cat": "M\u00e9dical",
    "Emetteur": "Cour de cassation (Ch. Crim.)",
    "Destinataire": "S\u00e9bastien GRAZIDE",
    "Desc": "Arr9t n\u00b0 07-83.385 relatif \u00e0 la faute caract\u00e9ris\u00e9e de s\u00e9curit\u00e9 pour \u00e9quipements dangereux.",
    "Montant": "Non pr\u00e9cis\u00e9",
    "ITT": "",
    "RefPiece": "11",
    "Portee": "",
    "LienGDrive": "",
    "Statut": "Pr\u00e9c\u00e9dent juridique"
  },
  {
    "Id": "EVT-06",
    "DateHeure": "10/01/2017",
    "Evt": "Consolidation m\u00e9dicale",
    "Cat": "M\u00e9dical",
    "Emetteur": "Non mentionn\u00e9",
    "Destinataire": "S\u00e9bastien GRAZIDE",
    "Desc": "Date fix\u00e9e pour la consolidation de l'\u00e9tat de la victime",
    "Montant": "Non mentionn\u00e9",
    "ITT": "",
    "RefPiece": "14",
    "Portee": "",
    "LienGDrive": "",
    "Statut": "Valid\u00e9"
  },
  {
    "Id": "EVT-07",
    "DateHeure": "05/04/2018",
    "Evt": "Arr9t (Jurisprudence)",
    "Cat": "M\u00e9dical",
    "Emetteur": "Cour de cassation",
    "Destinataire": "S\u00e9bastien GRAZIDE",
    "Desc": "D\u00e9cisions n\u00b0 16-87.669 et 16-83.984 : responsabilit\u00e9 civile personnelle du dirigeant devant le juge p\u00e9nal.",
    "Montant": "Non pr\u00e9cis\u00e9",
    "ITT": "",
    "RefPiece": "11",
    "Portee": "",
    "LienGDrive": "",
    "Statut": "Pr\u00e9c\u00e9dent juridique"
  },
  {
    "Id": "EVT-08",
    "DateHeure": "02/03/2022",
    "Evt": "Arr9t (Jurisprudence)",
    "Cat": "M\u00e9dical",
    "Emetteur": "Cour de cassation (Civ. 3e)",
    "Destinataire": "S\u00e9bastien GRAZIDE",
    "Desc": "Arr9t n\u00b0 20-21.723 sur la d\u00e9signation d'un mandataire ad hoc pour une soci\u00e9t\u00e9 radi\u00e9e.",
    "Montant": "Non pr\u00e9cis\u00e9",
    "ITT": "",
    "RefPiece": "11",
    "Portee": "",
    "LienGDrive": "",
    "Statut": "Pr\u00e9c\u00e9dent juridique"
  },
  {
    "Id": "EVT-09",
    "DateHeure": "04/04/2024",
    "Evt": "Arr9t (Jurisprudence)",
    "Cat": "M\u00e9dical",
    "Emetteur": "Cour de cassation (Civ. 2e)",
    "Destinataire": "S\u00e9bastien GRAZIDE",
    "Desc": "Arr9t n\u00b0 22-19.307 relatif \u00e0 la capitalisation sans contr\u00f4le de l'assureur.",
    "Montant": "Non pr\u00e9cis\u00e9",
    "ITT": "",
    "RefPiece": "11",
    "Portee": "",
    "LienGDrive": "",
    "Statut": "Pr\u00e9c\u00e9dent juridique"
  },
  {
    "Id": "EVT-10",
    "DateHeure": "mai 2026",
    "Evt": "M\u00e9mo sur les indemnit\u00e9s journali\u00e8res",
    "Cat": "M\u00e9dical",
    "Emetteur": "CPAM Haute-Garonne",
    "Destinataire": "Travailleur Ind\u00e9pendant",
    "Desc": "Document informatif g\u00e9n\u00e9ral (R\u00e9f. CPAM 31_2399_05/26).",
    "Montant": "IJ max: 197,51 \u20ac/jour ; IJ min: 6,28 \u20ac/jour",
    "ITT": "D\u00e9lai de carence de 3 jours",
    "RefPiece": "78, 79",
    "Portee": "",
    "LienGDrive": "",
    "Statut": ""
  },
  {
    "Id": "EVT-11",
    "DateHeure": "2026-05-29 15:00",
    "Evt": "Accident corporel",
    "Cat": "Fait G\u00e9n\u00e9rateur",
    "Emetteur": "SAS LES MAUVAIS GAR\u00c7ONS",
    "Destinataire": "S\u00e9bastien GRAZIDE",
    "Desc": "Chute d'une vasque en c\u00e9ramique bris\u00e9e provoquant une section tendineuse et nerveuse profonde \u00e0 la main droite (index).",
    "Montant": "",
    "ITT": "",
    "RefPiece": "PV n\u00b0 2026/015967",
    "Portee": "Fait g\u00e9n\u00e9rateur engageant la responsabilit\u00e9 civile objective (1242 al. 1 C.civ) et p\u00e9nale du tiers.",
    "LienGDrive": "https://drive.google.com/file/d/1v8lH68IWOfvFtu7EtU3wcpQTBIXAlwKI/view",
    "Statut": "Fait"
  },
  {
    "Id": "EVT-12",
    "DateHeure": "2026-05-29 15:20",
    "Evt": "Remboursement prestation Wero",
    "Cat": "Financier",
    "Emetteur": "Ayoub Bennourine (Coiffeur)",
    "Destinataire": "S\u00e9bastien GRAZIDE",
    "Desc": "Remboursement des 15\u20ac de la coupe de cheveux via Wero suite \u00e0 l'accident.",
    "Montant": "15.00 \u20ac (Cr\u00e9dit)",
    "ITT": "",
    "RefPiece": "Wero IPR000297029234",
    "Portee": "Reconnaissance tacite imm\u00e9diate de l'accident et preuve de pr\u00e9sence commerciale dans le salon.",
    "LienGDrive": "https://drive.google.com/file/d/1dQlB-56-h1A_kFvz0Y5n3Lh6z8yD6O9a/view",
    "Statut": "Fait"
  },
  {
    "Id": "EVT-13",
    "DateHeure": "2026-05-29 16:30",
    "Evt": "Soins d'urgence m\u00e9dicale",
    "Cat": "M\u00e9dical",
    "Emetteur": "Dr Julie JARDON (Centre Ari\u00e9geois de Soins Imm\u00e9diats)",
    "Destinataire": "S\u00e9bastien GRAZIDE",
    "Desc": "Exploration de la plaie palmaire profonde, lavage et d\u00e9sinfection au Dakin sous anesth\u00e9sie locale. R\u00e9f\u00e9rence d'urgence chirurgicale.",
    "Montant": "156.00 \u20ac (Prise en charge CSS)",
    "ITT": "",
    "RefPiece": "RPPS 10005156871 / R\u00e9f AM 2702 2615240013761",
    "Portee": "Certificat m\u00e9dical initial obligatoire fixant la mat\u00e9rialit\u00e9 imm\u00e9diate des l\u00e9sions.",
    "LienGDrive": "https://drive.google.com/file/d/1dQlB-56-h1A_kFvz0Y5n3Lh6z8yD6O9a/view",
    "Statut": "Fait"
  },
  {
    "Id": "EVT-14",
    "DateHeure": "2026-05-30",
    "Evt": "Intervention chirurgicale microchirurgie",
    "Cat": "M\u00e9dical",
    "Emetteur": "Dr Iskander DJERBI (SOS Main Clinique de l'Union)",
    "Destinataire": "S\u00e9bastien GRAZIDE",
    "Desc": "Suture chirurgicale (6 brins) du tendon fl\u00e9chisseur superficiel index droit, suture des paquets collat\u00e9raux et neurolyse du nerf.",
    "Montant": "814.16 \u20ac (100% CSS)",
    "ITT": "Repos post-op\u00e9ratoire",
    "RefPiece": "IPP : 2600014397 / CCAM : MJCA003JK",
    "Portee": "Acte op\u00e9ratoire lourd mat\u00e9rialisant l'atteinte physique grave fondant le pr\u00e9judice corporel.",
    "LienGDrive": "https://drive.google.com/file/d/1v8lH68IWOfvFtu7EtU3wcpQTBIXAlwKI/view",
    "Statut": "Fait"
  },
  {
    "Id": "EVT-15",
    "DateHeure": "2026-05-30",
    "Evt": "Consultation Sp\u00e9cifique Anesth\u00e9sie (U03)",
    "Cat": "M\u00e9dical",
    "Emetteur": "Dr Roland GAU (Clinique de l'Union)",
    "Destinataire": "S\u00e9bastien GRAZIDE",
    "Desc": "Consultation li\u00e9e \u00e0 l'hospitalisation d'urgence.",
    "Montant": "40.00 \u20ac",
    "ITT": "N/A",
    "RefPiece": "R\u00e9f AM 2852 2616010001578",
    "Portee": "\u00c9tablit le suivi clinique complet li\u00e9 \u00e0 l'acte op\u00e9ratoire.",
    "LienGDrive": "https://drive.google.com/file/d/1dQlB-56-h1A_kFvz0Y5n3Lh6z8yD6O9a/view",
    "Statut": "Fait"
  },
  {
    "Id": "EVT-16",
    "DateHeure": "30/05/2026",
    "Evt": "Frais de s\u00e9jour et soins (GHS)",
    "Cat": "M\u00e9dical",
    "Emetteur": "Clinique de l'Union",
    "Destinataire": "S\u00e9bastien GRAZIDE",
    "Desc": "Enregistrement administratif et soins lors de l'admission; Dossier CPAM n\u00b0 31727387.",
    "Montant": "814,16",
    "ITT": "",
    "RefPiece": "4",
    "Portee": "",
    "LienGDrive": "",
    "Statut": "Pay\u00e9"
  },
  {
    "Id": "EVT-17",
    "DateHeure": "2026-06-01",
    "Evt": "Arr\u00eat de travail initial (ITT)",
    "Cat": "M\u00e9dical",
    "Emetteur": "Dr Yogan OXYBEL (RPPS 10101732609)",
    "Destinataire": "S\u00e9bastien GRAZIDE",
    "Desc": "Prescription d'un arr\u00eat de travail initial de 15 jours suite aux l\u00e9sions de la main droite.",
    "Montant": "Indemnit\u00e9s \u00e0 calculer",
    "ITT": "Du 29/05/2026 au 12/06/2026 (15 jours)",
    "RefPiece": "Document_8.pdf",
    "Portee": "Justification de l'incapacit\u00e9 de travail initiale pour un informaticien droitier ind\u00e9pendant.",
    "LienGDrive": "https://drive.google.com/file/d/1dQlB-56-h1A_kFvz0Y5n3Lh6z8yD6O9a/view",
    "Statut": "Fait"
  },
  {
    "Id": "EVT-18",
    "DateHeure": "2026-06-01",
    "Evt": "Signalement administratif",
    "Cat": "Proc\u00e9dure",
    "Emetteur": "S\u00e9bastien GRAZIDE",
    "Destinataire": "Mairie de Foix (Adjoint M. Tavella)",
    "Desc": "Envoi d'un signalement officiel concernant la dangerosit\u00e9 du mat\u00e9riel et l'accident grave au salon.",
    "Montant": "",
    "ITT": "",
    "RefPiece": "secretariat@mairie-foix.fr",
    "Portee": "Alerte de s\u00e9curit\u00e9 publique pour contr\u00f4le administratif de l'ERP.",
    "LienGDrive": "https://drive.google.com/file/d/1dQlB-56-h1A_kFvz0Y5n3Lh6z8yD6O9a/view",
    "Statut": "Fait"
  },
  {
    "Id": "EVT-19",
    "DateHeure": "01/06/2026",
    "Evt": "Signalement d'accident grave et Dossier de Plainte P\u00e9nale",
    "Cat": "Proc\u00e9dure",
    "Emetteur": "S\u00e9bastien Grazide",
    "Destinataire": "Mairie de Foix / Services de Police / Procureur",
    "Desc": "Requ\u00eate de v\u00e9rification du num\u00e9ro de dossier CPAM 31727387. Zone l\u00e9s\u00e9e : main droite.",
    "Montant": "Pr\u00e9judice financier (perte de CA)",
    "ITT": "15 jours",
    "RefPiece": "2, 34, 35",
    "Portee": "",
    "LienGDrive": "",
    "Statut": ""
  },
  {
    "Id": "EVT-20",
    "DateHeure": "2026-06-02",
    "Evt": "R\u00e9quisition Judiciaire m\u00e9dicale",
    "Cat": "Proc\u00e9dure",
    "Emetteur": "Police Nationale / APJ J. Rodriguez Caparros",
    "Destinataire": "UMJ (M\u00e9decin L\u00e9giste)",
    "Desc": "D\u00e9livrance d'une r\u00e9quisition officielle pour examen m\u00e9dical afin de d\u00e9terminer l'ITT p\u00e9nale r\u00e9elle.",
    "Montant": "",
    "ITT": "",
    "RefPiece": "20260602 RF Requisition A Personne",
    "Portee": "Base l\u00e9gale pour \u00e9valuer objectivement la gravit\u00e9 des pr\u00e9judices physiques subis.",
    "LienGDrive": "https://drive.google.com/file/d/1dQlB-56-h1A_kFvz0Y5n3Lh6z8yD6O9a/view",
    "Statut": "Fait"
  },
  {
    "Id": "EVT-21",
    "DateHeure": "2026-06-02",
    "Evt": "Relev\u00e9s de prestations CPAM",
    "Cat": "Financier",
    "Emetteur": "CPAM de la Haute-Garonne",
    "Destinataire": "S\u00e9bastien GRAZIDE",
    "Desc": "Prise en charge des soins d'urgence (18,00 \u20ac pharmacie + 115,56 \u20ac Dr Jardon).",
    "Montant": "133.56 \u20ac (Total)",
    "ITT": "",
    "RefPiece": "Dossier CPAM TP",
    "Portee": "Preuve financi\u00e8re des premiers remboursements sociaux.",
    "LienGDrive": "https://drive.google.com/file/d/1dQlB-56-h1A_kFvz0Y5n3Lh6z8yD6O9a/view",
    "Statut": "Fait"
  },
  {
    "Id": "EVT-22",
    "DateHeure": "02/06/2026",
    "Evt": "Information sur les droits des victimes",
    "Cat": "M\u00e9dical",
    "Emetteur": "Minist\u00e8re de l'Int\u00e9rieur / Police Nationale",
    "Destinataire": "S\u00e9bastien GRAZIDE",
    "Desc": "Remise du r\u00e9c\u00e9piss\u00e9 et d'une note d'information sur les droits (avocat, indemnisation, aide juridictionnelle)",
    "Montant": "Gratuit",
    "ITT": "",
    "RefPiece": "7",
    "Portee": "",
    "LienGDrive": "",
    "Statut": "Document transmis par voie num\u00e9rique"
  },
  {
    "Id": "EVT-23",
    "DateHeure": "02/06/2026",
    "Evt": "Remboursement de prestations",
    "Cat": "Financier",
    "Emetteur": "CPAM de Haute-Garonne",
    "Destinataire": "S\u00e9bastien GRAZIDE",
    "Desc": "Versement global incluant la part compl\u00e9mentaire pour les soins du 29/05/2026.",
    "Montant": "18",
    "ITT": "",
    "RefPiece": "22",
    "Portee": "",
    "LienGDrive": "",
    "Statut": "R\u00e9gl\u00e9"
  },
  {
    "Id": "EVT-24",
    "DateHeure": "02/06/2026",
    "Evt": "Relev\u00e9s de prestations - Tiers Payant",
    "Cat": "Financier",
    "Emetteur": "CPAM de la Haute-Garonne",
    "Destinataire": "S\u00e9bastien Grazide / Pharmacie",
    "Desc": "Num\u00e9ro de dossier 31727387 absent des documents (seul le NIR est pr\u00e9sent).",
    "Montant": "18,00 \u20ac (Pharmacie) / 115,56 \u20ac (Dr Jardon)",
    "ITT": "Not in source",
    "RefPiece": "41, 42",
    "Portee": "",
    "LienGDrive": "",
    "Statut": ""
  },
  {
    "Id": "EVT-25",
    "DateHeure": "2026-06-02 10:00",
    "Evt": "D\u00e9p\u00f4t de plainte p\u00e9nale",
    "Cat": "Proc\u00e9dure",
    "Emetteur": "S\u00e9bastien GRAZIDE",
    "Destinataire": "H\u00f4tel de Police (Toulouse Rive Droite)",
    "Desc": "Plainte officielle pour blessures involontaires par manquement d\u00e9lib\u00e9r\u00e9 \u00e0 une obligation de s\u00e9curit\u00e9.",
    "Montant": "",
    "ITT": "",
    "RefPiece": "PV n\u00b0 2026/015967",
    "Portee": "D\u00e9clenche l'action publique et l'enqu\u00eate judiciaire p\u00e9nale.",
    "LienGDrive": "https://drive.google.com/file/d/1dQlB-56-h1A_kFvz0Y5n3Lh6z8yD6O9a/view",
    "Statut": "En cours"
  },
  {
    "Id": "EVT-26",
    "DateHeure": "2026-06-03",
    "Evt": "Ouverture dossier Recours contre Tiers",
    "Cat": "Proc\u00e9dure",
    "Emetteur": "CPAM de la Haute-Garonne",
    "Destinataire": "S\u00e9bastien GRAZIDE",
    "Desc": "Attestation de d\u00e9p\u00f4t - D\u00e9claration de recours contre tiers enregistr\u00e9e suite au signalement sur Ameli.",
    "Montant": "100% de remboursement",
    "ITT": "",
    "RefPiece": "Dossier n\u00b0 31727387 / 31713398",
    "Portee": "Active la proc\u00e9dure de subrogation de l'assurance maladie pour la r\u00e9cup\u00e9ration des d\u00e9bours.",
    "LienGDrive": "https://drive.google.com/file/d/1dQlB-56-h1A_kFvz0Y5n3Lh6z8yD6O9a/view",
    "Statut": "Valid\u00e9"
  },
  {
    "Id": "COR-01",
    "DateHeure": "03/06/2026",
    "Evt": "Envoi de l'arr\u00eat de travail",
    "Cat": "Correspondance",
    "Emetteur": "S\u00e9bastien GRAZIDE",
    "Destinataire": "CPAM de la Haute-Garonne",
    "Desc": "Exp\u00e9dition des volets 1 et 2 apr\u00e8s correction manuelle de l'erreur de date (mai au lieu de juin).",
    "Montant": "Non pr\u00e9cis\u00e9",
    "ITT": "",
    "RefPiece": "5",
    "Portee": "",
    "LienGDrive": "",
    "Statut": "\u00c0 faire (Urgent)"
  },
  {
    "Id": "COR-02",
    "DateHeure": "D'ici le 05/06/2026",
    "Evt": "D\u00e9claration de sinistre corporel",
    "Cat": "Correspondance",
    "Emetteur": "Assurances priv\u00e9es du patient",
    "Destinataire": "S\u00e9bastien GRAZIDE",
    "Desc": "Information de la protection juridique ou pr\u00e9voyance (limite l\u00e9gale de 5 jours).",
    "Montant": "Non pr\u00e9cis\u00e9",
    "ITT": "",
    "RefPiece": "5",
    "Portee": "",
    "LienGDrive": "",
    "Statut": "\u00c0 faire"
  },
  {
    "Id": "EVT-27",
    "DateHeure": "05/06/2026",
    "Evt": "D\u00e9p\u00f4t l\u00e9gal officiel du recommand\u00e9",
    "Cat": "M\u00e9dical",
    "Emetteur": "Plateforme Industrielle Courrier (LOGNES PIC)",
    "Destinataire": "S\u00e9bastien GRAZIDE",
    "Desc": "Date de flashage officielle retenue par la CPAM \u00e0 18h37.",
    "Montant": "Non pr\u00e9cis\u00e9",
    "ITT": "",
    "RefPiece": "6",
    "Portee": "",
    "LienGDrive": "",
    "Statut": "Fait"
  },
  {
    "Id": "COR-03",
    "DateHeure": "05/06/2026",
    "Evt": "Envoi recommand\u00e9 (LRAR)",
    "Cat": "Correspondance",
    "Emetteur": "S\u00e9bastien GRAZIDE",
    "Destinataire": "CPAM de la Haute-Garonne / Lognes PIC",
    "Desc": "Envoi d'un arr\u00eat de travail. Num\u00e9ro de LR : 870014140507947.",
    "Montant": "8.43",
    "ITT": "",
    "RefPiece": "18",
    "Portee": "",
    "LienGDrive": "",
    "Statut": "Exp\u00e9di\u00e9"
  },
  {
    "Id": "EVT-28",
    "DateHeure": "05/06/2026",
    "Evt": "Preuve de d\u00e9p\u00f4t LRAR (Avis d'arr\u00eat de travail)",
    "Cat": "M\u00e9dical",
    "Emetteur": "La Poste (Automate Blagnac)",
    "Destinataire": "CPAM de la Haute-Garonne",
    "Desc": "D\u00e9calage de date : Vignette du 03/06 mais flash postal le 05/06 (risque de hors-d\u00e9lai).",
    "Montant": "8,43 \u20ac (Frais d'envoi)",
    "ITT": "Prolongation \u00e0 pr\u00e9voir",
    "RefPiece": "36, 46, 47",
    "Portee": "",
    "LienGDrive": "",
    "Statut": ""
  },
  {
    "Id": "EVT-29",
    "DateHeure": "10/06/2026",
    "Evt": "Relev\u00e9 de prestations",
    "Cat": "M\u00e9dical",
    "Emetteur": "Assurance Maladie (CPAM)",
    "Destinataire": "S\u00e9bastien GRAZIDE",
    "Desc": "Enregistrement de l'acte de chirurgie (ADC) du 30/05/2026.",
    "Montant": "561,1",
    "ITT": "",
    "RefPiece": "4",
    "Portee": "",
    "LienGDrive": "",
    "Statut": "Fait"
  },
  {
    "Id": "EVT-30",
    "DateHeure": "10/06/2026",
    "Evt": "D\u00e9tail des versements / Tiers-Payant (Frais de s\u00e9jour et actes chirurgicaux)",
    "Cat": "Financier",
    "Emetteur": "Agent CPAM / Clinique de l'Union",
    "Destinataire": "S\u00e9bastien Grazide",
    "Desc": "Co\u00fbts rattach\u00e9s au dossier de recours n\u00b0 31727387. Confirme la chirurgie au 30/05/2026.",
    "Montant": "1 522,24 \u20ac (Total : 814,16 \u20ac GHS + 561,10 \u20ac ADC + 106,98 \u20ac ADC + 40,00 \u20ac APC)",
    "ITT": "Not in source",
    "RefPiece": "19, 48-51",
    "Portee": "",
    "LienGDrive": "",
    "Statut": ""
  },
  {
    "Id": "EVT-31",
    "DateHeure": "2026-06-12",
    "Evt": "Prolongation Arr\u00eat de Travail",
    "Cat": "M\u00e9dical",
    "Emetteur": "Dr Yogan OXYBEL",
    "Destinataire": "S\u00e9bastien GRAZIDE",
    "Desc": "T\u00e9l\u00e9consultation actant la continuit\u00e9 de l'incapacit\u00e9 de travail de la victime.",
    "Montant": "",
    "ITT": "Du 13/06/2026 au 23/06/2026 (11 jours)",
    "RefPiece": "AAT-AS-013118954-260612",
    "Portee": "Maintient la continuit\u00e9 m\u00e9dicale face aux assurances.",
    "LienGDrive": "https://drive.google.com/file/d/1dQlB-56-h1A_kFvz0Y5n3Lh6z8yD6O9a/view",
    "Statut": "Fait"
  },
  {
    "Id": "EVT-32",
    "DateHeure": "Avant le 12/06/2026",
    "Evt": "Consultation de contr\u00f4le",
    "Cat": "M\u00e9dical",
    "Emetteur": "Dr Yogan Oxybel (Blagnac)",
    "Destinataire": "S\u00e9bastien GRAZIDE",
    "Desc": "Planification de la prolongation n\u00e9cessaire de l'arr\u00eat de travail.",
    "Montant": "Non pr\u00e9cis\u00e9",
    "ITT": "",
    "RefPiece": "6",
    "Portee": "",
    "LienGDrive": "",
    "Statut": "\u00c0 faire"
  },
  {
    "Id": "EVT-33",
    "DateHeure": "12/06/2026",
    "Evt": "Consultation vid\to",
    "Cat": "M\u00e9dical",
    "Emetteur": "Dr Yogan Oxybel",
    "Destinataire": "S\u00e9bastien GRAZIDE",
    "Desc": "Rendez-vous de suivi m\tdical confirm",
    "Montant": "",
    "ITT": "",
    "RefPiece": "",
    "Portee": "",
    "LienGDrive": "",
    "Statut": ""
  },
  {
    "Id": "COR-04",
    "DateHeure": "16/06/2026",
    "Evt": "Demande de renseignements (Recours contre Tiers)",
    "Cat": "Correspondance",
    "Emetteur": "Sigrid Desbois (CPAM Haute-Garonne)",
    "Destinataire": "S\u00e9bastien Grazide",
    "Desc": "INCOH\u00c9RENCE MAJEURE  : La CPAM cite le dossier n\u00b0 2631103960 au lieu du n\u00b0 31727387 cible.",
    "Montant": "Not in source",
    "ITT": "Not in source",
    "RefPiece": "3, 4, 24, 48, 55-57",
    "Portee": "",
    "LienGDrive": "",
    "Statut": ""
  },
  {
    "Id": "COR-05",
    "DateHeure": "18/06/2026",
    "Evt": "Note de cadrage m\u00e9dico-l\u00e9gale et transmission de pi\u00e8ces",
    "Cat": "Correspondance",
    "Emetteur": "S\u00e9bastien Grazide",
    "Destinataire": "Sigrid Desbois (CPAM - P\u00f4le RCT 31)",
    "Desc": "RECTIFICATION  : Zone l\u00e9s\u00e9e confirm\u00e9e comme l' Index droit  (invalide l'erreur auriculaire). R\u00e9f\u00e9rence Recours 31727387 confirm\u00e9e.",
    "Montant": "Rappel des 814,16 \u20ac de frais de s\u00e9jour",
    "ITT": "Prolongation jusqu'au 23/06/2026",
    "RefPiece": "3, 4, 24, 48, 58-60",
    "Portee": "",
    "LienGDrive": "",
    "Statut": ""
  },
  {
    "Id": "EVT-34",
    "DateHeure": "19/06/2026",
    "Evt": "Rectification administrative",
    "Cat": "M\u00e9dical",
    "Emetteur": "Secr\u00e9tariat du Dr Djerbi",
    "Destinataire": "S\u00e9bastien GRAZIDE",
    "Desc": "Correction du compte-rendu op\u00e9ratoire : index droit au lieu du 5e doigt et date du 30/05 r\u00e9tablie.",
    "Montant": "Non pr\u00e9cis\u00e9",
    "ITT": "",
    "RefPiece": "4",
    "Portee": "",
    "LienGDrive": "",
    "Statut": "Fait"
  },
  {
    "Id": "EVT-35",
    "DateHeure": "19/06/2026",
    "Evt": "Remerciements pour CRO rectifi\u00e9 et note clinique de suivi \u00e0 J+20",
    "Cat": "M\u00e9dical",
    "Emetteur": "S\u00e9bastien Grazide / Secr\u00e9tariat Dr Djerbi",
    "Destinataire": "Dr Iskander Djerbi",
    "Desc": "RECTIFICATION CRUCIALE  : Zone l\u00e9s\u00e9e requalifi\u00e9e en  Index droit . Date chirurgicale rectifi\u00e9e au 30/05/2026. Dossier CPAM 31727387 valid\u00e9.",
    "Montant": "Prise en charge 100% (CSS)",
    "ITT": "Not in source",
    "RefPiece": "19, 61-65",
    "Portee": "",
    "LienGDrive": "",
    "Statut": ""
  },
  {
    "Id": "EVT-36",
    "DateHeure": "2026-06-23",
    "Evt": "Contr\u00f4le post-op\u00e9ratoire et Prolongation",
    "Cat": "M\u00e9dical",
    "Emetteur": "Dr Iskander DJERBI",
    "Destinataire": "S\u00e9bastien GRAZIDE",
    "Desc": "Constatation clinique de persistance des paresth\u00e9sies et hypoesth\u00e9sie. Prolongation de l'arr\u00eat de travail.",
    "Montant": "",
    "ITT": "Du 24/06/2026 au 23/07/2026 (30 jours)",
    "RefPiece": "IPP 2600014397",
    "Portee": "\u00c9tablit la dur\u00e9e totale d'ITT de 56 jours et la persistance des s\u00e9quelles nerveuses.",
    "LienGDrive": "https://drive.google.com/file/d/1dQlB-56-h1A_kFvz0Y5n3Lh6z8yD6O9a/view",
    "Statut": "Fait"
  },
  {
    "Id": "EVT-37",
    "DateHeure": "23/06/2026",
    "Evt": "S\u00e9ance de r\u00e9\u00e9ducation (Kin\u00e9sith\u00e9rapie)",
    "Cat": "M\u00e9dical",
    "Emetteur": "Clinique de l'Union (B\u00e2timent B, 2\u00e8me \u00e9tage)",
    "Destinataire": "S\u00e9bastien GRAZIDE",
    "Desc": "Premier rendez-vous de r\u00e9\u00e9ducation sp\u00e9cialis\u00e9e de la main \u00e0 16h15.",
    "Montant": "Non pr\u00e9cis\u00e9",
    "ITT": "",
    "RefPiece": "5",
    "Portee": "",
    "LienGDrive": "",
    "Statut": "Pr\u00e9vu"
  },
  {
    "Id": "EVT-38",
    "DateHeure": "23/06/2026",
    "Evt": "Consultation de contr\u00f4le post-op\u00e9ratoire (J+24)",
    "Cat": "M\u00e9dical",
    "Emetteur": "Dr Iskander Djerbi",
    "Destinataire": "S\u00e9bastien GRAZIDE",
    "Desc": "Bonne \u00e9volution cicatricielle ; d\u00e9ficit neurologique (insensibilit\u00e9) not\u00e9",
    "Montant": "Non sp\u00e9cifi\u00e9",
    "ITT": "",
    "RefPiece": "10",
    "Portee": "",
    "LienGDrive": "",
    "Statut": "R\u00e9alis\u00e9"
  },
  {
    "Id": "COR-06",
    "DateHeure": "2026-06-24",
    "Evt": "Transmission de pi\u00e8ces CPAM",
    "Cat": "Correspondance",
    "Emetteur": "S\u00e9bastien GRAZIDE",
    "Destinataire": "CPAM / Sigrid DESBOIS",
    "Desc": "Envoi \u00e9lectronique des pi\u00e8ces m\u00e9dicales et d'identit\u00e9 pour le dossier RCT.",
    "Montant": "",
    "ITT": "",
    "RefPiece": "LRE n\u00b0 870014219039071",
    "Portee": "S\u00e9curise le suivi administratif et garantit la subrogation de la CPAM.",
    "LienGDrive": "https://drive.google.com/file/d/1dQlB-56-h1A_kFvz0Y5n3Lh6z8yD6O9a/view",
    "Statut": "Fait"
  },
  {
    "Id": "EVT-39",
    "DateHeure": "24/06/2026",
    "Evt": "D\u00e9marche administrative / Email",
    "Cat": "Proc\u00e9dure",
    "Emetteur": "S\u00e9bastien Grazide (Assur\u00e9)",
    "Destinataire": "S\u00e9bastien GRAZIDE",
    "Desc": "Envoi des pi\u00e8ces justificatives \u00e0 l'Assurance Maladie pour recours contre tiers",
    "Montant": "Non sp\u00e9cifi\u00e9",
    "ITT": "",
    "RefPiece": "10",
    "Portee": "",
    "LienGDrive": "",
    "Statut": "Envoy\u00e9"
  },
  {
    "Id": "COR-07",
    "DateHeure": "24/06/2026",
    "Evt": "Envoi d'\u00e9l\u00e9ments m\u00e9dicaux compl\u00e9mentaires (J+24 Post-Op)",
    "Cat": "Correspondance",
    "Emetteur": "S\u00e9bastien Grazide",
    "Destinataire": "Sigrid Desbois (CPAM - P\u00f4le RCT 31)",
    "Desc": "Utilisation du num\u00e9ro de dossier 31727387 comme r\u00e9f\u00e9rence globale. Confirmation l\u00e9sion Index droit.",
    "Montant": "Honoraires et frais de transport \u00e0 rattacher",
    "ITT": "Prolongation jusqu'au 23/07/2026",
    "RefPiece": "15, 69, 73-75",
    "Portee": "",
    "LienGDrive": "",
    "Statut": ""
  },
  {
    "Id": "EVT-40",
    "DateHeure": "25/06/2026",
    "Evt": "Confirmation de rendez-vous Kin\u00e9sith\u00e9rapie",
    "Cat": "M\u00e9dical",
    "Emetteur": "Doctolib (pour J. Milas)",
    "Destinataire": "S\u00e9bastien Grazide",
    "Desc": "R\u00e9\u00e9ducation cibl\u00e9e suite \u00e0 la chirurgie de l'index.",
    "Montant": "Not in source",
    "ITT": "Not in source",
    "RefPiece": "76, 77",
    "Portee": "",
    "LienGDrive": "",
    "Statut": ""
  },
  {
    "Id": "COR-08",
    "DateHeure": "2026-06-29",
    "Evt": "Envoi Mise en demeure SAS",
    "Cat": "Correspondance",
    "Emetteur": "S\u00e9bastien GRAZIDE",
    "Destinataire": "SAS LES MAUVAIS GAR\u00c7ONS",
    "Desc": "Envoi de la lettre recommand\u00e9e r\u00e9clamant les coordonn\u00e9es de l'assurance et 5000 \u20ac de provision.",
    "Montant": "5 000.00 \u20ac (Demand\u00e9)",
    "ITT": "",
    "RefPiece": "Suivi : 87001424863012T",
    "Portee": "Fait courir le d\u00e9lai amiable de 15 jours. Date d'\u00e9ch\u00e9ance au 14 juillet 2026.",
    "LienGDrive": "https://drive.google.com/file/d/1ig96EJZFO5yqZcYnkJl7g2urAuTxkZLn/view",
    "Statut": "Distribu\u00e9"
  },
  {
    "Id": "COR-09",
    "DateHeure": "2026-06-29",
    "Evt": "Envoi Mise en demeure Pr\u00e9sident SABIR",
    "Cat": "Correspondance",
    "Emetteur": "S\u00e9bastien GRAZIDE",
    "Destinataire": "M. Mountasser SABIR",
    "Desc": "Mise en demeure personnelle pour faute d\u00e9tachable li\u00e9e \u00e0 la s\u00e9curit\u00e9 et au d\u00e9faut d'assurance.",
    "Montant": "35 900.00 \u20ac (Vis\u00e9)",
    "ITT": "",
    "RefPiece": "Suivi : 87001424862879J",
    "Portee": "Mise en cause personnelle sur le patrimoine du Pr\u00e9sident. \u00c9ch\u00e9ance le 14 juillet 2026.",
    "LienGDrive": "https://drive.google.com/file/d/117sFmGu7yFbYzd0VrKYNSCK_tDYHugrL/view",
    "Statut": "Distribu\u00e9"
  },
  {
    "Id": "COR-10",
    "DateHeure": "2026-06-29",
    "Evt": "Envoi Mise en demeure DG ANDISSAC",
    "Cat": "Correspondance",
    "Emetteur": "S\u00e9bastien GRAZIDE",
    "Destinataire": "Mme ADUSSAC",
    "Desc": "Mise en demeure personnelle pour faute d\u00e9tachable li\u00e9e \u00e0 la s\u00e9curit\u00e9 et au d\u00e9faut d'assurance.",
    "Montant": "35 900.00 \u20ac (Vis\u00e9)",
    "ITT": "",
    "RefPiece": "Suivi : 87001424721856G",
    "Portee": "Mise en cause personnelle sur le patrimoine de la Directrice G\u00e9n\u00e9rale. \u00c9ch\u00e9ance le 14 juillet 2026.",
    "LienGDrive": "https://drive.google.com/file/d/1EcEmT59OVPSiVTf9pK9gKwCYcBHSJ_93/view",
    "Statut": "Distribu\u00e9"
  },
  {
    "Id": "COR-11",
    "DateHeure": "2026-06-29",
    "Evt": "Envoi Mise en demeure Bailleur",
    "Cat": "Correspondance",
    "Emetteur": "S\u00e9bastien GRAZIDE",
    "Destinataire": "M. Romain DELRIEU",
    "Desc": "Demande de communication de son contrat d'assurance propri\u00e9taire non-occupant.",
    "Montant": "",
    "ITT": "",
    "RefPiece": "Suivi : 87001424862462Y",
    "Portee": "Mise en cause du bailleur pour d\u00e9faut d'entretien structurel de la plomberie. \u00c9ch\u00e9ance le 14 juillet 2026.",
    "LienGDrive": "https://drive.google.com/file/d/114JeqDjs9-0PRC_PHQrBxH1CZ3PoZgIv/view",
    "Statut": "Distribu\u00e9"
  },
  {
    "Id": "COR-12",
    "DateHeure": "2026-06-29",
    "Evt": "Action Directe Assureur RC",
    "Cat": "Correspondance",
    "Emetteur": "S\u00e9bastien GRAZIDE",
    "Destinataire": "L'ASSUREUR (Assureur)",
    "Desc": "Courrier d'action directe en responsabilit\u00e9 (Art. L. 124-3 du Code des assurances) visant le paiement de l'indemnit\u00e9 globale r\u00e9vis\u00e9e.",
    "Montant": "35 900.00 \u20ac (Chiffr\u00e9)",
    "ITT": "",
    "RefPiece": "Suivi : 1-5wPPbmfrpP4UzFCysGMYgaThI4wZfkZOQ7Gg1IQ7Bg",
    "Portee": "Consacre l'action directe autonome contre l'assureur. L'arr\u00eat Cass. Civ. 2e, 15 juin 2023 (n\u00b0 21-14.197) garantit la r\u00e9ouverture en cas d'aggravation future post-transaction.",
    "LienGDrive": "https://drive.google.com/file/d/1-5wPPbmfrpP4UzFCysGMYgaThI4wZfkZOQ7Gg1IQ7Bg/view",
    "Statut": "Envoi effectu\u00e9"
  },
  {
    "Id": "COR-13",
    "DateHeure": "2026-06-29",
    "Evt": "Transmission plainte au Procureur",
    "Cat": "Proc\u00e9dure",
    "Emetteur": "S\u00e9bastien GRAZIDE",
    "Destinataire": "Procureur de la R\u00e9publique (Foix)",
    "Desc": "Transmission officielle du dossier p\u00e9nal et du compl\u00e9ment de plainte pour manquement de s\u00e9curit\u00e9.",
    "Montant": "",
    "ITT": "",
    "RefPiece": "Suivi : 87001424923505I",
    "Portee": "Saisine du parquet correctionnel de Foix.",
    "LienGDrive": "https://drive.google.com/file/d/1-lV1A6Eg9cbUI-NTE-cAJZU8ZWElCy4K/view",
    "Statut": "Distribu\u00e9"
  },
  {
    "Id": "COR-14",
    "DateHeure": "2026-06-30",
    "Evt": "Transmission CPAM et AR",
    "Cat": "Correspondance",
    "Emetteur": "S\u00e9bastien GRAZIDE",
    "Destinataire": "CPAM de l'Ari\u00e8ge",
    "Desc": "D\u00e9claration compl\u00e9mentaire d'accident et justificatifs de soins.",
    "Montant": "",
    "ITT": "",
    "RefPiece": "Suivi : 87001421903907",
    "Portee": "Avis de r\u00e9ception officiel du dossier de subrogation sociale.",
    "LienGDrive": "https://drive.google.com/file/d/1JaXhfYjJOQD3q0p-bz2CKMntj7AcCfZY/view",
    "Statut": "AR Re\u00e7u"
  },
  {
    "Id": "COR-15",
    "DateHeure": "2026-07-14",
    "Evt": "\u00c9ch\u00e9ance l\u00e9gale de mise en demeure",
    "Cat": "\u00c9ch\u00e9ance",
    "Emetteur": "S\u00e9bastien GRAZIDE",
    "Destinataire": "SAS, Sabir, Andissac, Delrieu",
    "Desc": "Fin du d\u00e9lai amiable de 15 jours calendaires.",
    "Montant": "35 900.00 \u20ac (Total)",
    "ITT": "",
    "RefPiece": "D\u00e9lai de courtoisie",
    "Portee": "Condition pr\u00e9alable marquant l'ouverture de la voie judiciaire contentieuse.",
    "LienGDrive": "N/A",
    "Statut": "\u00c0 venir"
  },
  {
    "Id": "EVT-41",
    "DateHeure": "2026-07-15",
    "Evt": "Lancement de l'assignation en r\u00e9f\u00e9r\u00e9",
    "Cat": "Proc\u00e9dure",
    "Emetteur": "S\u00e9bastien GRAZIDE",
    "Destinataire": "Commissaire de Justice (\u00c9tude LAPORTE)",
    "Desc": "Signification par huissier de l'assignation en r\u00e9f\u00e9r\u00e9-provision et r\u00e9f\u00e9r\u00e9-communication.",
    "Montant": "5 000.00 \u20ac (Provision)",
    "ITT": "",
    "RefPiece": "Projet Assignation V1",
    "Portee": "Saisine du Tribunal judiciaire de Foix pour forcer la production de la police d'assurance et verser une provision.",
    "LienGDrive": "https://docs.google.com/document/d/1J1bmCek8imtkgJnXniJg-9RXNapGjzTvnxJPgF_HFh4/edit",
    "Statut": "\u00c0 venir"
  },
  {
    "Id": "EVT-42",
    "DateHeure": "2026-07-31",
    "Evt": "Audience de r\u00e9f\u00e9r\u00e9-communication",
    "Cat": "Proc\u00e9dure",
    "Emetteur": "S\u00e9bastien GRAZIDE",
    "Destinataire": "SAS / Dirigeants / l'assureur",
    "Desc": "Audience devant le Tribunal judiciaire de Foix pour obtenir la communication forc\u00e9e de la police d'assurance sous astreinte.",
    "Montant": "150.00 \u20ac / jour d'astreinte",
    "ITT": "",
    "RefPiece": "R\u00e9f\u00e9r\u00e9-communication",
    "Portee": "Obtention sous astreinte de 150 \u20ac/jour de la copie int\u00e9grale de la police d'assurance de la SAS aupr\u00e8s des dirigeants de droit, \u00e0 d\u00e9faut de r\u00e9ponse de la l'assureur.",
    "LienGDrive": "N/A",
    "Statut": "\u00c0 venir"
  },
  {
    "Id": "EVT-43",
    "DateHeure": "12/11/2026",
    "Evt": "Expertise m\u00e9dicale l\u00e9gale",
    "Cat": "M\u00e9dical",
    "Emetteur": "UMJ de Purpan",
    "Destinataire": "S\u00e9bastien GRAZIDE",
    "Desc": "Examen pour fixer le taux d'incapacit\u00e9 et l'ITT r\u00e9elle; PV n\u00b0 2026/015967.",
    "Montant": "Non pr\u00e9cis\u00e9",
    "ITT": "",
    "RefPiece": "4",
    "Portee": "",
    "LienGDrive": "",
    "Statut": "\u00c0 venir"
  },
  {
    "Id": "EVT-44",
    "DateHeure": "12/11/2026",
    "Evt": "Examen m\u00e9dical l\u00e9gal",
    "Cat": "M\u00e9dical",
    "Emetteur": "UMJ de l'H\u00f4pital de Purpan",
    "Destinataire": "S\u00e9bastien GRAZIDE",
    "Desc": "Examen \u00e0 13h45 (B\u00e2timent Raymonde Fournet) pour \u00e9valuation de l'ITT.",
    "Montant": "Non pr\u00e9cis\u00e9",
    "ITT": "",
    "RefPiece": "5",
    "Portee": "",
    "LienGDrive": "",
    "Statut": "Pr\u00e9vu"
  },
  {
    "Id": "EVT-45",
    "DateHeure": "2026-11-12 13:45",
    "Evt": "Expertise M\u00e9dicale Judiciaire",
    "Cat": "M\u00e9dical",
    "Emetteur": "UMJ H\u00f4pital Purpan (Toulouse)",
    "Destinataire": "S\u00e9bastien GRAZIDE",
    "Desc": "Examen clinique et sur dossier par le m\u00e9decin l\u00e9giste expert d\u00e9sign\u00e9 pour fixer d\u00e9finitivement les pr\u00e9judices physiques et l'ITT p\u00e9nale.",
    "Montant": "",
    "ITT": "",
    "RefPiece": "B\u00e2timent Raymonde Fournet",
    "Portee": "Acte d\u00e9cisif pour l'\u00e9valuation contradictoire d\u00e9finitive de tous les postes de pr\u00e9judice (DFP, Souffrances, Agr\u00e9ment).",
    "LienGDrive": "https://drive.google.com/file/d/1dQlB-56-h1A_kFvz0Y5n3Lh6z8yD6O9a/view",
    "Statut": "Programm\u00e9"
  },
  {
    "Id": "EVT-46",
    "DateHeure": "Non pr\u00e9cis\u00e9",
    "Evt": "Soins infirmiers (pansements)",
    "Cat": "M\u00e9dical",
    "Emetteur": "Cabinet infirmier Rue Mathieu Lanes (Toulouse)",
    "Destinataire": "S\u00e9bastien GRAZIDE",
    "Desc": "Pansements post-chirurgicaux lourds toutes les 48 heures.",
    "Montant": "Pris en charge \u00e0 100% (CSS)",
    "ITT": "",
    "RefPiece": "6",
    "Portee": "",
    "LienGDrive": "",
    "Statut": "En cours"
  },
  {
    "Id": "EVT-47",
    "DateHeure": "Non pr\u00e9cis\u00e9e",
    "Evt": "Soins et remboursements (G\u00e9n\u00e9ralit\u00e9s)",
    "Cat": "Financier",
    "Emetteur": "CPAM (n\u00b0 31727387 et 2631103960)",
    "Destinataire": "S\u00e9bastien GRAZIDE",
    "Desc": "Frais pharmaceutiques, hospitalisation et arr\u00eats de travail li\u00e9s au pr\u00e9judice corporel",
    "Montant": "Non pr\u00e9cis\u00e9",
    "ITT": "",
    "RefPiece": "7",
    "Portee": "",
    "LienGDrive": "",
    "Statut": "\u00c0 convoquer en cas d'audience (d\u00e9claration de jugement commun)"
  },
  {
    "Id": "EVT-48",
    "DateHeure": "Non pr\u00e9cis\u00e9e (Post-accident)",
    "Evt": "Analyse de sinistre corporel",
    "Cat": "M\u00e9dical",
    "Emetteur": "SAS LES MAUVAIS GARCONS",
    "Destinataire": "S\u00e9bastien GRAZIDE",
    "Desc": "Accident li\u00e9 \u00e0 une vasque en c\u00e9ramique bris\u00e9e tranchante (index droit impact\u00e9). Dossiers CPAM 31727387 / 2631103960.",
    "Montant": "Non pr\u00e9cis\u00e9",
    "ITT": "",
    "RefPiece": "Texte utilisateur, 22",
    "Portee": "",
    "LienGDrive": "",
    "Statut": "En cours / Litige"
  },
  {
    "Id": "EVT-49",
    "DateHeure": "Non pr\u00e9cis\u00e9e",
    "Evt": "Expertise m\u00e9dicale / Indemnisation",
    "Cat": "M\u00e9dical",
    "Emetteur": "Expert judiciaire / M\u00e9decin",
    "Destinataire": "S\u00e9bastien GRAZIDE",
    "Desc": "\u00c9valuation du DFP pour une victime de 44 ans (M. Grazide).",
    "Montant": "1 500 \u00e0 2 500 par point de DFP",
    "ITT": "",
    "RefPiece": "11",
    "Portee": "",
    "LienGDrive": "",
    "Statut": "\u00c0 r\u00e9aliser / Bar\u00e8me"
  },
  {
    "Id": "COR-16",
    "DateHeure": "Non sp\u00e9cifi\u00e9e",
    "Evt": "Action directe",
    "Cat": "M\u00e9dical",
    "Emetteur": "Assureur RC de la SAS",
    "Destinataire": "S\u00e9bastien GRAZIDE",
    "Desc": "Action prioritaire pour s\u00e9curiser le paiement des indemnit\u00e9s (fondement Article L. 124-3 du Code des assurances).",
    "Montant": "Non pr\u00e9cis\u00e9",
    "ITT": "",
    "RefPiece": "12",
    "Portee": "",
    "LienGDrive": "",
    "Statut": "Action strat\u00e9gique recommand\u00e9e"
  },
  {
    "Id": "EVT-50",
    "DateHeure": "Non sp\u00e9cifi\u00e9e",
    "Evt": "Plaidoirie / Action p\u00e9nale",
    "Cat": "M\u00e9dical",
    "Emetteur": "Tribunal correctionnel",
    "Destinataire": "S\u00e9bastien GRAZIDE",
    "Desc": "Poursuites pour blessures involontaires (Art. 222-20 CP) contre le dirigeant et le pr\u00e9pos\u00e9.",
    "Montant": "Non pr\u00e9cis\u00e9",
    "ITT": "",
    "RefPiece": "12",
    "Portee": "",
    "LienGDrive": "",
    "Statut": "Action envisag\u00e9e"
  },
  {
    "Id": "EVT-51",
    "DateHeure": "Non sp\u00e9cifi\u00e9e",
    "Evt": "Requ\u00eate en d\u00e9signation d'un mandataire ad hoc",
    "Cat": "M\u00e9dical",
    "Emetteur": "Tribunal de commerce",
    "Destinataire": "S\u00e9bastien GRAZIDE",
    "Desc": "Proc\u00e9dure n\u00e9cessaire en cas de radiation de la SAS LES MAUVAIS GARCONS pour expertise m\u00e9dicale.",
    "Montant": "Non pr\u00e9cis\u00e9",
    "ITT": "",
    "RefPiece": "12",
    "Portee": "",
    "LienGDrive": "",
    "Statut": "Proc\u00e9dure indispensable"
  },
  {
    "Id": "EVT-52",
    "DateHeure": "Non sp\u00e9cifi\u00e9e",
    "Evt": "Analyse du pr\u00e9judice professionnel",
    "Cat": "M\u00e9dical",
    "Emetteur": "M. Grazide (Informaticien ind\u00e9pendant)",
    "Destinataire": "S\u00e9bastien GRAZIDE",
    "Desc": "\u00c9valuation de l'impact de l'accident sur la capacit\u00e9 \u00e0 exercer son m\u00e9tier d'informaticien.",
    "Montant": "Non pr\u00e9cis\u00e9",
    "ITT": "",
    "RefPiece": "12",
    "Portee": "",
    "LienGDrive": "",
    "Statut": "En cours d'\u00e9valuation"
  },
  {
    "Id": "EVT-53",
    "DateHeure": "Non sp\u00e9cifi\u00e9e",
    "Evt": "Expertise m\u00e9dicale (Pr\u00e9judices extra-patrimoniaux)",
    "Cat": "M\u00e9dical",
    "Emetteur": "M\u00e9decin expert (Expertise m\u00e9dicale l\u00e9gale)",
    "Destinataire": "S\u00e9bastien GRAZIDE",
    "Desc": "\u00c9valuation du DFP (D\u00e9ficit Fonctionnel Permanent) estim\u00e9 entre 1 500 \u20ac et 2 500 \u20ac par point pour un homme de 44 ans.",
    "Montant": "1 500 - 2 500 par point de DFP",
    "ITT": "",
    "RefPiece": "12",
    "Portee": "",
    "LienGDrive": "",
    "Statut": "Base d'indemnisation"
  },
  {
    "Id": "EVT-54",
    "DateHeure": "Non sp\u00e9cifi\u00e9e",
    "Evt": "Pr\u00e9servation des droits",
    "Cat": "M\u00e9dical",
    "Emetteur": "Tribunal",
    "Destinataire": "S\u00e9bastien GRAZIDE",
    "Desc": "Insertion de r\u00e9serves judiciaires pour l'aggravation future de l'\u00e9tat fonctionnel de la main dominante.",
    "Montant": "Non pr\u00e9cis\u00e9",
    "ITT": "",
    "RefPiece": "12",
    "Portee": "",
    "LienGDrive": "",
    "Statut": "Mesure conservatoire"
  },
  {
    "Id": "EVT-55",
    "DateHeure": "\u00c0 l'audience",
    "Evt": "Demande de provision et d\u00e9signation d'expert",
    "Cat": "M\u00e9dical",
    "Emetteur": "Tribunal Correctionnel de Foix",
    "Destinataire": "S\u00e9bastien GRAZIDE",
    "Desc": "Demande d'une provision financi\u00e8re de 5 000 \u20ac et d'une expertise judiciaire m\u00e9dicale.",
    "Montant": "5 000",
    "ITT": "",
    "RefPiece": "15",
    "Portee": "",
    "LienGDrive": "",
    "Statut": "En attente de jugement"
  },
  {
    "Id": "EVT-56",
    "DateHeure": "\u00c0 l'audience",
    "Evt": "Demande d'indemnit\u00e9 (Art. 475-1 du CPP)",
    "Cat": "M\u00e9dical",
    "Emetteur": "Tribunal Correctionnel de Foix",
    "Destinataire": "S\u00e9bastien GRAZIDE",
    "Desc": "Condamnation solidaire des pr\u00e9venus aux frais de justice.",
    "Montant": "3 000",
    "ITT": "",
    "RefPiece": "15",
    "Portee": "",
    "LienGDrive": "",
    "Statut": "En attente de jugement"
  },
  {
    "Id": "EVT-57",
    "DateHeure": "Non pr\u00e9cis\u00e9e dans la source",
    "Evt": "Consultation et prescription d'arr\u00eat de travail",
    "Cat": "M\u00e9dical",
    "Emetteur": "Dr Oxybel",
    "Destinataire": "S\u00e9bastien GRAZIDE",
    "Desc": "Prescription initiale de 25 jours d'arr\u00eat de travail suite \u00e0 l'accident.",
    "Montant": "Non pr\u00e9cis\u00e9 dans la source",
    "ITT": "",
    "RefPiece": "17",
    "Portee": "",
    "LienGDrive": "",
    "Statut": "Termin\u00e9"
  },
  {
    "Id": "EVT-58",
    "DateHeure": "Non pr\u00e9cis\u00e9e dans la source",
    "Evt": "\u00c9valuation des Pertes de Gains Professionnels Actuels (PGPA)",
    "Cat": "M\u00e9dical",
    "Emetteur": "Non pr\u00e9cis\u00e9 (Expertise juridique)",
    "Destinataire": "S\u00e9bastien GRAZIDE",
    "Desc": "Perte d'exploitation durant l'incapacit\u00e9 temporaire totale de travail (25 jours).",
    "Montant": "7 500 \u20ac",
    "ITT": "",
    "RefPiece": "17",
    "Portee": "",
    "LienGDrive": "",
    "Statut": "Chiffrage estimatif"
  },
  {
    "Id": "EVT-59",
    "DateHeure": "Non pr\u00e9cis\u00e9e dans la source",
    "Evt": "\u00c9valuation des Souffrances Endur\u00e9es",
    "Cat": "M\u00e9dical",
    "Emetteur": "Expert m\u00e9dical l\u00e9giste",
    "Destinataire": "S\u00e9bastien GRAZIDE",
    "Desc": "Douleurs physiques et chirurgicales \u00e9valu\u00e9es \u00e0 4/7 sur l'\u00e9chelle de douleur.",
    "Montant": "12 000 \u20ac",
    "ITT": "",
    "RefPiece": "17",
    "Portee": "",
    "LienGDrive": "",
    "Statut": "Chiffrage estimatif"
  },
  {
    "Id": "EVT-60",
    "DateHeure": "Non pr\u00e9cis\u00e9e dans la source",
    "Evt": "D\u00e9penses de Sant\u00e9 Futures (DSF)",
    "Cat": "M\u00e9dical",
    "Emetteur": "Non pr\u00e9cis\u00e9",
    "Destinataire": "S\u00e9bastien GRAZIDE",
    "Desc": "Acquisition de mat\u00e9riels d'adaptation ergonomiques (claviers et souris sp\u00e9cialis\u00e9s).",
    "Montant": "15 000 \u20ac",
    "ITT": "",
    "RefPiece": "17",
    "Portee": "",
    "LienGDrive": "",
    "Statut": "Chiffrage prospectif"
  },
  {
    "Id": "EVT-61",
    "DateHeure": "Non pr\u00e9cis\u00e9e dans la source",
    "Evt": "Frais de justice (Article 475-1)",
    "Cat": "M\u00e9dical",
    "Emetteur": "Avocat / Tribunal",
    "Destinataire": "S\u00e9bastien GRAZIDE",
    "Desc": "Frais de proc\u00e9dure et honoraires d'avocat pour la d\u00e9fense des int\u00e9r\u00eats de M. Grazide.",
    "Montant": "3 000 \u20ac",
    "ITT": "",
    "RefPiece": "17",
    "Portee": "",
    "LienGDrive": "",
    "Statut": "Demande en justice"
  },
  {
    "Id": "EVT-62",
    "DateHeure": "Non mentionn\u00e9",
    "Evt": "Indemnisation (Arr\u00e9rages)",
    "Cat": "M\u00e9dical",
    "Emetteur": "Fonds de garantie (FGTI)",
    "Destinataire": "S\u00e9bastien GRAZIDE",
    "Desc": "Somme allou\u00e9e au titre des arr\u00e9rages \u00e9chus des d\u00e9penses de sant\u00e9 futures",
    "Montant": "345 275,62",
    "ITT": "",
    "RefPiece": "14",
    "Portee": "",
    "LienGDrive": "",
    "Statut": "Annul\u00e9 par cassation"
  }
]